pixhash/__init__.py
pixhash/cli.py
pixhash/extractor.py
pixhash-1.0.0.dist-info/licenses/LICENSE
pixhash-1.0.0.dist-info/METADATA
pixhash-1.0.0.dist-info/WHEEL
pixhash-1.0.0.dist-info/entry_points.txt
pixhash-1.0.0.dist-info/top_level.txt
pixhash-1.0.0.dist-info/RECORD
