Metadata-Version: 2.4
Name: pixhash
Version: 1.0.0
Summary: CTI tool to extract and hash images from websites
Author-email: Faisal Albuloushi <SQL@hotmail.co.uk>
License: MIT
Requires-Python: >=3.8
License-File: LICENSE
Dynamic: license-file
